antares_http/__init__.py
antares_http/antares.py
antares_http-1.1.4.dist-info/LICENSE
antares_http-1.1.4.dist-info/METADATA
antares_http-1.1.4.dist-info/WHEEL
antares_http-1.1.4.dist-info/top_level.txt
antares_http-1.1.4.dist-info/RECORD
