Metadata-Version: 2.1
Name: antares-http
Version: 1.1.4
Summary: A Python Library to simplify connection to Antares IoT Platform
Home-page: https://github.com/antaresdocumentation/antares-python
Author: Antares Support Team
Author-email: support@antares.id
License: UNKNOWN
Platform: UNKNOWN
Classifier: Programming Language :: Python :: 3
Classifier: Programming Language :: Python :: 2.7
Classifier: License :: OSI Approved :: MIT License
Classifier: Operating System :: OS Independent
Requires-Dist: requests
